dj_ec_idcardfield/__init__.py
dj_ec_idcardfield/apps.py
dj_ec_idcardfield/forms.py
dj_ec_idcardfield/locale/en/LC_MESSAGES/django.mo
dj_ec_idcardfield/locale/en/LC_MESSAGES/django.po
dj_ec_idcardfield/locale/es/LC_MESSAGES/django.mo
dj_ec_idcardfield/locale/es/LC_MESSAGES/django.po
dj_ec_idcardfield/models.py
dj_ec_idcardfield/serializers.py
dj_ec_idcardfield/validators.py
dj_ec_idcardfield-0.1.1.dist-info/LICENSE
dj_ec_idcardfield-0.1.1.dist-info/METADATA
dj_ec_idcardfield-0.1.1.dist-info/WHEEL
dj_ec_idcardfield-0.1.1.dist-info/RECORD
