Metadata-Version: 2.1
Name: dj-ec-idcardfield
Version: 0.1.1
Summary: An Idcard and RUC field for Ecuador for Django Models, Forms, and Serializers.
Home-page: https://github.com/hugofer93/dj-ec-idcardfield
License: MIT
Author: Hugo Silva Álvarez
Author-email: hugofer93@gmail.com
Requires-Python: >=3.8
Classifier: Development Status :: 5 - Production/Stable
Classifier: Environment :: Web Environment
Classifier: Framework :: Django
Classifier: Framework :: Django :: 4.2
Classifier: Framework :: Django :: 5.0
Classifier: Framework :: Django :: 5.1
Classifier: Framework :: Django :: 5.2
Classifier: Intended Audience :: Developers
Classifier: License :: OSI Approved :: MIT License
Classifier: Operating System :: OS Independent
Classifier: Programming Language :: Python :: 3
Classifier: Programming Language :: Python :: 3.8
Classifier: Programming Language :: Python :: 3.9
Classifier: Programming Language :: Python :: 3.10
Classifier: Programming Language :: Python :: 3.11
Classifier: Programming Language :: Python :: 3.12
Classifier: Programming Language :: Python :: 3 :: Only
Classifier: Programming Language :: Python :: 3.13
Classifier: Topic :: Internet :: WWW/HTTP
Provides-Extra: djangorestframework
Project-URL: Documentation, https://hugofer93.github.io/dj-ec-idcardfield/
Project-URL: Repository, https://github.com/hugofer93/dj-ec-idcardfield
